README
setup.py
PyNodeCDN.egg-info/PKG-INFO
PyNodeCDN.egg-info/SOURCES.txt
PyNodeCDN.egg-info/dependency_links.txt
PyNodeCDN.egg-info/requires.txt
PyNodeCDN.egg-info/top_level.txt
pynodecdn/__init__.py
pynodecdn/PyNodeServer/__init__.py