Metadata-Version: 1.1
Name: PyNodeCDN
Version: 0.0.13
Summary: A simple implementation for webservers that provides a cool, consistent route to NodeCDN on your site.
Home-page: UNKNOWN
Author: Eric Vicente
Author-email: justaneric.c@gmail.com
License: MIT
Keywords: JavaScript,Python,Webserver,Development
Platform: UNKNOWN
Classifier: Development Status :: 5 - Production/Stable
Classifier: Intended Audience :: Developers
Classifier: License :: OSI Approved :: MIT License
Classifier: Programming Language :: Python :: 3
